espressomaker/__init__.py
espressomaker/espresso.py
espressomaker-0.1b2.dist-info/LICENSE
espressomaker-0.1b2.dist-info/METADATA
espressomaker-0.1b2.dist-info/WHEEL
espressomaker-0.1b2.dist-info/top_level.txt
espressomaker-0.1b2.dist-info/RECORD
