Metadata-Version: 2.1
Name: espressomaker
Version: 0.1b2
Summary: Allows to temporarily modify the power management settings on a MacOS to run processes uninterruptedly.
Home-page: https://github.com/rmoralesdelgado/espressomaker
Author: Raul Morales Delgado
Author-email: rmoralesdelgado@gmail.com
License: UNKNOWN
Platform: UNKNOWN
Classifier: Programming Language :: Python :: 3
Classifier: License :: OSI Approved :: MIT License
Classifier: Natural Language :: English
Classifier: Operating System :: MacOS :: MacOS X
Classifier: Intended Audience :: Developers
Classifier: Intended Audience :: Science/Research
Requires-Python: >=3.5
